lab2/code/InstrFetch/InstrMem.sv
/*****************************************************************************
  File Name:    InstrMem.sv
  Author:       Chenxu Jiang
                DingCheng Hu
  Date:         Apr 29, 2017
  Description:  Instruction memory
                Input   program counter value
                output  Instruction bit code at position
*****************************************************************************/
module InstrMem (
  input[7:0]    pc,                     // pc value 8-bit
  output[8:0]   instr                   // machine code at pc
);

  reg[8:0]      instrMem[0:255];        // ROM array
  assign        instr = instrMem[pc];   //read from the address

  initial begin
    $readmemh("test.instr", instrMem);
  end

endmodule

lab2/code/InstrFetch/ProgramCounter.sv
/*****************************************************************************
  File Name:    ProgramCounter.sv
  Author:       Chenxu Jiang
                DingCheng Hu
  Date:         Apr 29, 2017
  Description:  Program Counter
                Input   branchAddr, halt, init, isBranch, CLK
                Output  pcAddr
*****************************************************************************/
module ProgramCounter (
  input[7:0]    branchAddr,       // possible branch addr to take
  input         halt,             // freeze pc if true
  input         init,             // initialize
  input         isBranch,         // if take the branch
  input         CLK,
  output  reg[7:0]  pcAddr        // output address
);

  always @(posedge CLK) begin
    if(init) begin                // init
      pcAddr <= 0;

    end else if(halt) begin       // halt
      pcAddr <= pcAddr;

    end else if(isBranch) begin   // take branch
      pcAddr <= branchAddr;

    end else begin                //increment
      pcAddr <= pcAddr + 1;
    end
  end
endmodule

lab2/code/InstrFetch/LookupTable.sv
/*****************************************************************************
  File Name:    LookupTable.sv
  Author:       Chenxu Jiang
                DingCheng Hu
  Date:         Apr 29, 2017
  Description:  lookup table stores 4 8-bit instr address for branching
                Take 2-bit control signal, output 8-bit address
*****************************************************************************/
module LookupTable(
  input[1:0]    control,    // 2-bit control signal
  output[7:0]   branch      // 8-bit pc to jump to
);

  // declare an 8 bit register with 4 entries
  reg[7:0]      branches[0:3];

  // assign the pc_addr
  assign        branch = branches[control];

  initial begin
    $readmemh("test.branch", branches);
  end

endmodule

lab2/code/InstrFetch/InstrFetch.sv
/*****************************************************************************
  File Name:    InstrFetch.sv
  Author:       Chenxu Jiang
                DingCheng Hu
  Date:         Apr 29, 2017
  Description:  Combination of PC, instruction memory and lookup Table;
                Input   CLK, isBranch, Branch
                Output  Instruction bit code.
*****************************************************************************/
`include "ProgramCounter.sv"
`include "InstrMem.sv"
`include "LookupTable.sv"

module InstrFetch (
  input         init,                   // initial set pc to 0
  input         halt,                   // halt pc, make pc stay.
  input         isBranch,               // 1 bit, if need branch
  input         resultALU,              // 1 bit ALU calc if branch taken
  input[1:0]    branchCtrl,             // 2-bit, which branch to take
  input         CLK,
  output[8:0]   Instr                   // output 9 bit instruction code
);

  // wires: program counter and branchaddress
  wire[7:0]     PC, branch;
  wire          writePC;

  // wiring
  assign        writePC = isBranch & resultALU;

  // connect modules
  LookupTable branchTable(branchCtrl, branch);
  ProgramCounter intPC(branch, halt, init, writePC, CLK, PC);
  InstrMem InMem(PC, Instr);

endmodule

lab2/code/InstrFetch/InstrFetch_tb.sv
/*****************************************************************************
  File Name:    InstrFetch.sv
  Author:       Chenxu Jiang
                DingCheng Hu
  Date:         Apr 29, 2017
  Description:  Combination of PC, instruction memory and lookup Table;
                Input   CLK, isBranch, Branch
                Output  Instruction bit code.
*****************************************************************************/
`timescale 1ns / 100ps
`include "InstrFetch.sv"

module InstrFetch_tb;

  reg           init, halt, isBranch, resultALU, CLK;
  reg[1:0]      branchCtrl;
  wire[8:0]     instr;

  InstrFetch IFTest(init, halt, isBranch, resultALU, branchCtrl, CLK, instr);

  always begin
    #5 CLK = 1;
    #5 CLK = 0;
  end

  initial begin
    $dumpfile("InstrFetchTest.vcd");
    $dumpvars(0, InstrFetch_tb);

    init = 1'b1;

    #10;        // initialize
    halt = 1'b0; isBranch = 1'b0; init = 1'b0;
    $strobe("Instr = %b (000000000)", instr);

    #5;        // let clock run
    $strobe("Instr = %b (000000001)", instr);

    #10;        // let clock run
    $strobe("Instr = %b (000000010)", instr);

    #10;        // let clock run
    $strobe("Instr = %b (000000011)", instr);

    #10;        // let clock run
    $strobe("Instr = %b (000000100)", instr);

    #10;        // try failed branch
    isBranch = 1'b1; resultALU = 1'b0;
    $strobe("Instr = %b (000000101)", instr);

    #10;        // try successfull branch
    resultALU = 1'b1; branchCtrl = 2'b01;
    $strobe("Instr = %b (000000011)", instr);

    #10;        // test halt
    halt = 1'b1;
    $strobe("Instr = %b (000000011)", instr);

    #10;
    $strobe("Instr = %b (000000011)", instr);

    #10;
    $finish;
  end

endmodule

lab2/code/InstrFetch/InstrFetchTest.vcd
$date
	Mon May  8 17:10:42 2017
$end
$version
	Icarus Verilog
$end
$timescale
	100ps
$end
$scope module InstrFetch_tb $end
$var wire 9 ! instr [8:0] $end
$var reg 1 " CLK $end
$var reg 2 # branchCtrl [1:0] $end
$var reg 1 $ halt $end
$var reg 1 % init $end
$var reg 1 & isBranch $end
$var reg 1 ' resultALU $end
$scope module IFTest $end
$var wire 1 " CLK $end
$var wire 2 ( branchCtrl [1:0] $end
$var wire 1 $ halt $end
$var wire 1 % init $end
$var wire 1 & isBranch $end
$var wire 1 ' resultALU $end
$var wire 1 ) writePC $end
$var wire 8 * branch [7:0] $end
$var wire 8 + PC [7:0] $end
$var wire 9 , Instr [8:0] $end
$scope module InMem $end
$var wire 9 - instr [8:0] $end
$var wire 8 . pc [7:0] $end
$upscope $end
$scope module branchTable $end
$var wire 8 / branch [7:0] $end
$var wire 2 0 control [1:0] $end
$upscope $end
$scope module intPC $end
$var wire 1 " CLK $end
$var wire 8 1 branchAddr [7:0] $end
$var wire 1 $ halt $end
$var wire 1 % init $end
$var wire 1 ) isBranch $end
$var reg 8 2 pcAddr [7:0] $end
$upscope $end
$upscope $end
$upscope $end
$enddefinitions $end
#0
$dumpvars
bx 2
bx 1
bx 0
bx /
bx .
bx -
bx ,
bx +
bx *
x)
bx (
x'
x&
1%
x$
bx #
x"
bx !
$end
#50
b0 !
b0 ,
b0 -
b0 +
b0 .
b0 2
1"
#100
0)
0"
0%
0&
0$
#150
b1 !
b1 ,
b1 -
b1 +
b1 .
b1 2
1"
#200
0"
#250
b10 !
b10 ,
b10 -
b10 +
b10 .
b10 2
1"
#300
0"
#350
b11 !
b11 ,
b11 -
b11 +
b11 .
b11 2
1"
#400
0"
#450
b100 !
b100 ,
b100 -
b100 +
b100 .
b100 2
1"
#500
0"
#550
b101 !
b101 ,
b101 -
b101 +
b101 .
b101 2
1"
0'
1&
#600
0"
#650
b11 !
b11 ,
b11 -
b11 +
b11 .
b11 2
1)
1"
b11 *
b11 /
b11 1
b1 #
b1 (
b1 0
1'
#700
0"
#750
1"
1$
